curveplate/__init__.py
curveplate/cli.py
curveplate/dxf_export.py
curveplate/geometry.py
curveplate/pdf_export.py
curveplate/stp_export.py
curveplate-0.1.1.dist-info/licenses/LICENSE
curveplate-0.1.1.dist-info/METADATA
curveplate-0.1.1.dist-info/WHEEL
curveplate-0.1.1.dist-info/entry_points.txt
curveplate-0.1.1.dist-info/top_level.txt
curveplate-0.1.1.dist-info/RECORD
