Metadata-Version: 2.4
Name: curveplate
Version: 0.1.1
Summary: Generate model railway flexible track laying templates (DXF, PDF, STP)
Author: gsdali
License-Expression: MIT
Project-URL: Homepage, https://github.com/gsdali/curveplate
Project-URL: Repository, https://github.com/gsdali/curveplate
Project-URL: Issues, https://github.com/gsdali/curveplate/issues
Keywords: model railway,track template,DXF,CAD,laser cutting
Classifier: Development Status :: 3 - Alpha
Classifier: Intended Audience :: End Users/Desktop
Classifier: Programming Language :: Python :: 3.13
Classifier: Topic :: Scientific/Engineering :: Visualization
Requires-Python: >=3.13
License-File: LICENSE
Requires-Dist: ezdxf>=1.0.0
Requires-Dist: reportlab>=4.0.0
Requires-Dist: geomdl>=5.3.0
Provides-Extra: dev
Requires-Dist: pytest>=7.0.0; extra == "dev"
Requires-Dist: ruff>=0.1.0; extra == "dev"
Provides-Extra: stp
Requires-Dist: cadquery>=2.4.0; extra == "stp"
Dynamic: license-file
